discourse/__init__.py
discourse/category.py
discourse/client.py
discourse/jsonobject.py
discourse/notification.py
discourse/plugin.py
discourse/post.py
discourse/private_message.py
discourse/tag.py
discourse/topic.py
discourse/user.py
discourse-0.1.2.dist-info/LICENSE
discourse-0.1.2.dist-info/METADATA
discourse-0.1.2.dist-info/WHEEL
discourse-0.1.2.dist-info/top_level.txt
discourse-0.1.2.dist-info/RECORD
