Metadata-Version: 2.1
Name: discourse
Version: 0.1.2
Summary: A Python wrapper of the Discourse API
Home-page: https://github.com/samamorgan/discourse
Author: Sam Morgan
Author-email: sama4mail@gmail.com
License: UNKNOWN
Platform: UNKNOWN
Classifier: Programming Language :: Python :: 3
Classifier: License :: OSI Approved :: GNU General Public License v3 (GPLv3)
Classifier: Operating System :: OS Independent
Classifier: Development Status :: 3 - Alpha
Requires-Dist: requests
